<annotation>
	<folder>bag</folder>
	<filename>VID_20180112_114546111_069.jpg</filename>
	<path>C:\Users\jesus.moliname\Desktop\train\bag\VID_20180112_114546111_069.jpg</path>
	<source>
		<database>Unknown</database>
	</source>
	<size>
		<width>664</width>
		<height>1182</height>
		<depth>3</depth>
	</size>
	<segmented>0</segmented>
	<object>
		<name>bag</name>
		<pose>Unspecified</pose>
		<truncated>0</truncated>
		<difficult>0</difficult>
		<bndbox>
			<xmin>344</xmin>
			<ymin>619</ymin>
			<xmax>571</xmax>
			<ymax>829</ymax>
		</bndbox>
	</object>
	<object>
		<name>bin</name>
		<pose>Unspecified</pose>
		<truncated>1</truncated>
		<difficult>0</difficult>
		<bndbox>
			<xmin>1</xmin>
			<ymin>630</ymin>
			<xmax>131</xmax>
			<ymax>964</ymax>
		</bndbox>
	</object>
</annotation>
